odoo/addons/repair_type_refurbish/README.rst
odoo/addons/repair_type_refurbish/__init__.py
odoo/addons/repair_type_refurbish/__manifest__.py
odoo/addons/repair_type_refurbish/i18n/it.po
odoo/addons/repair_type_refurbish/i18n/repair_type_refurbish.pot
odoo/addons/repair_type_refurbish/models/__init__.py
odoo/addons/repair_type_refurbish/models/repair.py
odoo/addons/repair_type_refurbish/models/repair_type.py
odoo/addons/repair_type_refurbish/readme/CONFIGURE.rst
odoo/addons/repair_type_refurbish/readme/CONTRIBUTORS.rst
odoo/addons/repair_type_refurbish/readme/DESCRIPTION.rst
odoo/addons/repair_type_refurbish/readme/USAGE.rst
odoo/addons/repair_type_refurbish/static/description/icon.png
odoo/addons/repair_type_refurbish/static/description/index.html
odoo/addons/repair_type_refurbish/tests/__init__.py
odoo/addons/repair_type_refurbish/tests/test_repair_type.py
odoo/addons/repair_type_refurbish/views/repair_type.xml
odoo_addon_repair_type_refurbish-16.0.1.0.0.4.dist-info/METADATA
odoo_addon_repair_type_refurbish-16.0.1.0.0.4.dist-info/WHEEL
odoo_addon_repair_type_refurbish-16.0.1.0.0.4.dist-info/top_level.txt
odoo_addon_repair_type_refurbish-16.0.1.0.0.4.dist-info/RECORD
